rbintegrations/__init__.py
rbintegrations/deprecation.py
rbintegrations/extension.py
rbintegrations/__pycache__/__init__.cpython-312.pyc
rbintegrations/asana/__init__.py
rbintegrations/asana/fields.py
rbintegrations/asana/forms.py
rbintegrations/asana/integration.py
rbintegrations/asana/tests.py
rbintegrations/asana/urls.py
rbintegrations/asana/views.py
rbintegrations/basechat/__init__.py
rbintegrations/basechat/forms.py
rbintegrations/basechat/integration.py
rbintegrations/baseci/__init__.py
rbintegrations/baseci/errors.py
rbintegrations/baseci/forms.py
rbintegrations/baseci/integration.py
rbintegrations/baseci/tests/__init__.py
rbintegrations/baseci/tests/test_base_ci_integration.py
rbintegrations/circleci/__init__.py
rbintegrations/circleci/forms.py
rbintegrations/circleci/integration.py
rbintegrations/circleci/tests.py
rbintegrations/circleci/urls.py
rbintegrations/circleci/views.py
rbintegrations/discord/__init__.py
rbintegrations/discord/forms.py
rbintegrations/discord/integration.py
rbintegrations/discord/tests.py
rbintegrations/idonethis/__init__.py
rbintegrations/idonethis/entries.py
rbintegrations/idonethis/forms.py
rbintegrations/idonethis/integration.py
rbintegrations/idonethis/pages.py
rbintegrations/idonethis/tests.py
rbintegrations/idonethis/utils.py
rbintegrations/jenkinsci/__init__.py
rbintegrations/jenkinsci/api.py
rbintegrations/jenkinsci/forms.py
rbintegrations/jenkinsci/integration.py
rbintegrations/jenkinsci/tests.py
rbintegrations/matrix/__init__.py
rbintegrations/matrix/forms.py
rbintegrations/matrix/integration.py
rbintegrations/matrix/tests.py
rbintegrations/mattermost/__init__.py
rbintegrations/mattermost/integration.py
rbintegrations/mattermost/tests.py
rbintegrations/msteams/__init__.py
rbintegrations/msteams/forms.py
rbintegrations/msteams/integration.py
rbintegrations/msteams/tests.py
rbintegrations/slack/__init__.py
rbintegrations/slack/integration.py
rbintegrations/slack/tests.py
rbintegrations/static/staticfiles.json
rbintegrations-4.0.2.dist-info/AUTHORS
rbintegrations-4.0.2.dist-info/LICENSE
rbintegrations-4.0.2.dist-info/METADATA
rbintegrations-4.0.2.dist-info/WHEEL
rbintegrations-4.0.2.dist-info/entry_points.txt
rbintegrations-4.0.2.dist-info/top_level.txt
rbintegrations-4.0.2.dist-info/RECORD
