Metadata-Version: 2.1
Name: rbintegrations
Version: 4.0.2
Summary: A set of third-party service integrations for Review Board 5.0+.
Home-page: https://www.reviewboard.org/
Author: Beanbag, Inc.
Author-email: support@beanbaginc.com
Maintainer: Beanbag, Inc.
Maintainer-email: support@beanbaginc.com
Classifier: Development Status :: 5 - Production/Stable
Classifier: Environment :: Web Environment
Classifier: Framework :: Review Board
Classifier: Intended Audience :: Developers
Classifier: License :: OSI Approved :: MIT License
Classifier: Natural Language :: English
Classifier: Operating System :: OS Independent
Classifier: Programming Language :: Python
Classifier: Programming Language :: Python :: 3
Classifier: Programming Language :: Python :: 3.8
Classifier: Programming Language :: Python :: 3.9
Classifier: Programming Language :: Python :: 3.10
Classifier: Programming Language :: Python :: 3.11
Classifier: Programming Language :: Python :: 3.12
Classifier: Topic :: Communications :: Chat
Classifier: Topic :: Software Development :: Build Tools
Classifier: Topic :: Software Development :: Quality Assurance
Classifier: Topic :: Software Development :: Testing
Requires-Python: >=3.8
License-File: LICENSE
License-File: AUTHORS
Requires-Dist: asana ~=5.0.7
Requires-Dist: housekeeping ~=1.1
Requires-Dist: PyYAML >=3.12
